[
    {
     "title": "Killers of the Flower Moon (2023)",
     "movieID": "232014"
    },
    {
     "title": "The Nightmare Before Christmas 30th Anniversary (2023)",
     "movieID": "233197"
    },
    {
     "title": "Under the Light (2023)",
     "movieID": "233881"
    },
    {
     "title": "TAYLOR SWIFT | THE ERAS TOUR",
     "movieID": "23292"
    },
    {
     "title": "The Exorcist: Believer (2023)",
     "movieID": "231976"
    },
    {
     "title": "PAW Patrol: The Mighty Movie (2023)",
     "movieID": "232218"
    },
    {
     "title": "Saw X (2023)",
     "movieID": "232577"
    },
    {
     "title": "The Creator (2023)",
     "movieID": "231997"
    },
    {
     "title": "A Haunting in Venice (2023)",
     "movieID": "231120"
    },
    {
     "title": "Dumb Money (2023)",
     "movieID": "232282"
    },
    {
     "title": "Dicks: The Musical (2023)",
     "movieID": "232701"
    },
    {
     "title": "Barbie (2023)",
     "movieID": "185727"
    },
    {
     "title": "Back to the Future",
     "movieID": "50896"
    },
    {
     "title": "Soul Mates (2023)",
     "movieID": "233807"
    },
    {
     "title": "Hocus Pocus 30th Anniversary (2023)",
     "movieID": "233347"
    },
    {
     "title": "The Nun II (2023)",
     "movieID": "232432"
    },
    {
     "title": "The Equalizer 3 (2023)",
     "movieID": "227748"
    },
    {
     "title": "It (2017)",
     "movieID": "199151"
    },
    {
     "title": "Tiger Nageswara Rao (2023)",
     "movieID": "233759"
    },
    {
     "title": "LEO: Bloody Sweet (2023)",
     "movieID": "233473"
    },
    {
     "title": "Expend4bles (2023)",
     "movieID": "232154"
    },
    {
     "title": "Teenage Mutant Ninja Turtles: Mutant Mayhem (2023)",
     "movieID": "231059"
    },
    {
     "title": "Bhagavanth Kesari (2023)",
     "movieID": "232898"
    },
    {
     "title": "The Metropolitan Opera: Dead Man Walking",
     "movieID": "232271"
    },
    {
     "title": "The Canterville Ghost (2023)",
     "movieID": "233530"
    },
    {
     "title": "The Other Zoey (2023)",
     "movieID": "216918"
    },
    {
     "title": "Oppenheimer (2023)",
     "movieID": "230575"
    },
    {
     "title": "Nyad (2023)",
     "movieID": "233549"
    },
    {
     "title": "Ganapath (2023)",
     "movieID": "233633"
    },
    {
     "title": "Jawan (2023)",
     "movieID": "231675"
    },
    {
     "title": "The Blind (2023)",
     "movieID": "232024"
    },
    {
     "title": "Butcher's Crossing (2023)",
     "movieID": "233414"
    },
    {
     "title": "Pain Hustlers (2023)",
     "movieID": "233861"
    },
    {
     "title": "The Road Dance (2023)",
     "movieID": "233341"
    },
    {
     "title": "Foe (2023)",
     "movieID": "233161"
    },
    {
     "title": "She Came to Me (2023)",
     "movieID": "232097"
    },
    {
     "title": "Harry Potter and the Half-Blood Prince",
     "movieID": "99112"
    },
    {
     "title": "Back to the Future (2023 Re-Release)",
     "movieID": "232730"
    },
    {
     "title": "Blue Beetle (2023)",
     "movieID": "231534"
    },
    {
     "title": "Shelter in Solitude (2023)",
     "movieID": "2023"
    },
    {
     "title": "My Big Fat Greek Wedding 3 (2023)",
     "movieID": "231938"
    },
    {
     "title": "The Hill (2023)",
     "movieID": "232141"
    },
    {
     "title": "Moana (2016) \u2013 Disney100 Special Engagement",
     "movieID": "232297"
    },
    {
     "title": "Malibu Horror Story",
     "movieID": "227532"
    },
    {
     "title": "Yaariyan 2 (2023)",
     "movieID": "233634"
    },
    {
     "title": "When Evil Lurks (2023)",
     "movieID": "233462"
    },
    {
     "title": "Dear David (2023)",
     "movieID": "232580"
    },
    {
     "title": "Maujaan Hi Maujaan (2023)",
     "movieID": "233893"
    },
    {
     "title": "Gran Turismo: Based on a True Story (2023)",
     "movieID": "231714"
    }
   ]